mjf_finance/__init__.py
mjf_finance/distributions.py
mjf_finance/statistics.py
mjf_finance/utils.py
mjf_finance-0.1.0.dist-info/METADATA
mjf_finance-0.1.0.dist-info/WHEEL
mjf_finance-0.1.0.dist-info/licenses/LICENSE
mjf_finance-0.1.0.dist-info/RECORD
