Metadata-Version: 2.4
Name: mjf-finance
Version: 0.1.0
Summary: Modified Jones-Faddy Skew t-Distributions for Financial Modeling
Project-URL: Homepage, https://github.com/kuslavicek/mjf-finance
Project-URL: Bug Tracker, https://github.com/kuslavicek/mjf-finance/issues
Author-email: kuslavicek <kuslavicek@gmail.com>
License-Expression: MIT
License-File: LICENSE
Classifier: License :: OSI Approved :: MIT License
Classifier: Operating System :: OS Independent
Classifier: Programming Language :: Python :: 3
Classifier: Topic :: Office/Business :: Financial :: Investment
Classifier: Topic :: Scientific/Engineering :: Mathematics
Requires-Python: >=3.8
Requires-Dist: numpy
Requires-Dist: scipy
